clinphen-1.28.data/scripts/clinphen
clinphen-1.28.data/scripts/clinphen_bulk
clinphen_src/__init__.py
clinphen_src/get_phenotypes.py
clinphen_src/hpo_names.py
clinphen_src/hpo_setup.sh
clinphen_src/hpo_syns.py
clinphen_src/interface.py
clinphen_src/prep_thesaurus.py
clinphen_src/src_dir.py
clinphen_src/standardize_syn_map.py
clinphen_src/umls_thesaurus_extraction.sh
clinphen_src/umlshelp.py
clinphen_src/appJar/__init__.py
clinphen_src/appJar/appjar.py
clinphen_src/appJar/lib/TkDND_wrapper.py
clinphen_src/appJar/lib/__init__.py
clinphen_src/appJar/lib/nanojpeg.py
clinphen_src/appJar/lib/png.py
clinphen_src/appJar/lib/tkinter_png.py
clinphen_src/appJar/lib/tooltip.py
clinphen_src/appJar/tkinter/__init__.py
clinphen_src/appJar/tkinter/__main__.py
clinphen_src/appJar/tkinter/colorchooser.py
clinphen_src/appJar/tkinter/commondialog.py
clinphen_src/appJar/tkinter/constants.py
clinphen_src/appJar/tkinter/dialog.py
clinphen_src/appJar/tkinter/dnd.py
clinphen_src/appJar/tkinter/filedialog.py
clinphen_src/appJar/tkinter/font.py
clinphen_src/appJar/tkinter/messagebox.py
clinphen_src/appJar/tkinter/scrolledtext.py
clinphen_src/appJar/tkinter/simpledialog.py
clinphen_src/appJar/tkinter/tix.py
clinphen_src/appJar/tkinter/ttk.py
clinphen_src/data/.DS_Store
clinphen_src/data/common_phenotypes.txt
clinphen_src/data/example_record.txt
clinphen_src/data/hp.obo
clinphen_src/data/hpo_synonyms.txt
clinphen_src/data/hpo_term_names.txt
clinphen-1.28.dist-info/METADATA
clinphen-1.28.dist-info/WHEEL
clinphen-1.28.dist-info/top_level.txt
clinphen-1.28.dist-info/RECORD
