Metadata-Version: 2.1
Name: clinphen
Version: 1.28
Summary: An automatic phenotype extractor
Home-page: http://bejerano.stanford.edu/clinphen/
Author: Cole A. Deisseroth
Author-email: cdeisser@stanford.edu
License: UNKNOWN
Platform: UNKNOWN
Classifier: Programming Language :: Python :: 2.7
Classifier: Operating System :: OS Independent
Requires-Dist: nltk (>=3.4)
Requires-Dist: six (>=1.12.0)
Requires-Dist: pandas (>=0.20.1)
